readerllamaindex/pineconer.py
readerllamaindex-0.1.2.dist-info/METADATA
readerllamaindex-0.1.2.dist-info/WHEEL
readerllamaindex-0.1.2.dist-info/top_level.txt
readerllamaindex-0.1.2.dist-info/RECORD
