Metadata-Version: 2.4
Name: readerllamaindex
Version: 0.1.2
Summary: RAG读取与构建index知识库
Requires-Python: >=3.10
Requires-Dist: llama-index>=0.12.30
Requires-Dist: llama-index-vector-stores-pinecone>=0.4.5
Requires-Dist: llama-index-vector-stores-postgres>=0.4.2
Requires-Dist: pinecone>=6.0.2
Requires-Dist: python-dotenv>=1.1.0
Requires-Dist: toolsz>=0.1.2
